molass/__init__.py
molass/Backward/ConcTracker.py
molass/Backward/DecompResultAdapter.py
molass/Backward/MappedCurve.py
molass/Backward/MappedInfoProxy.py
molass/Backward/PreviewParams.py
molass/Backward/RankEstimator.py
molass/Backward/RgDiffRatios.py
molass/Backward/SerialDataProxy.py
molass/Baseline/Baseline2D.py
molass/Baseline/BaselineUtils.py
molass/Baseline/Basesurface.py
molass/Baseline/IntegralBaseline.py
molass/Baseline/LpmBaseline.py
molass/Baseline/SimpleBaseline.py
molass/Baseline/Surface.py
molass/Baseline/UvBaseline.py
molass/Baseline/UvDiffEffect.py
molass/Baseline/UvdiffBaseline.py
molass/Baseline/__init__.py
molass/Batch/V1Legacy.py
molass/Batch/V1Result.py
molass/Batch/__init__.py
molass/Bridge/LegacyBaselines.py
molass/Bridge/LegacyRgCurve.py
molass/Bridge/OptimizerInput.py
molass/Bridge/SdProxy.py
molass/Bridge/V2Result.py
molass/Bridge/__init__.py
molass/DataObjects/Curve.py
molass/DataObjects/SecSaxsData.py
molass/DataObjects/SsMatrixData.py
molass/DataObjects/UvData.py
molass/DataObjects/XrData.py
molass/DataObjects/__init__.py
molass/DataUtils/AnomalyHandlers.py
molass/DataUtils/Beamline.py
molass/DataUtils/ExportSsd.py
molass/DataUtils/FolderWalker.py
molass/DataUtils/ForwardCompat.py
molass/DataUtils/Outliers.py
molass/DataUtils/UvFileTrimming.py
molass/DataUtils/UvLoader.py
molass/DataUtils/XrLoader.py
molass/DataUtils/ZipFolder.py
molass/DataUtils/__init__.py
molass/Decompose/Partner.py
molass/Decompose/Proportional.py
molass/Decompose/VaryUtils.py
molass/Decompose/XrOnlyUtils.py
molass/Decompose/__init__.py
molass/DensitySpace/Densities.py
molass/DensitySpace/VoxelSpace.py
molass/DensitySpace/__init__.py
molass/Except/ExceptionTypes.py
molass/Except/__init__.py
molass/FlowChange/Differential.py
molass/FlowChange/FlowChange.py
molass/FlowChange/FlowChangeInfo.py
molass/FlowChange/FlowChangeJudge.py
molass/FlowChange/FlowChangeLikely.py
molass/FlowChange/FlowChangeParams.py
molass/FlowChange/FlowChangePlot.py
molass-0.8.1.dist-info/METADATA
molass-0.8.1.dist-info/WHEEL
molass-0.8.1.dist-info/licenses/LICENSE.txt
molass-0.8.1.dist-info/RECORD
