Metadata-Version: 2.4
Name: molass
Version: 0.8.1
Summary: Matrix Optimization with Low-rank factorization for Automated analysis of SEC-SAXS
Project-URL: Repository, https://github.com/biosaxs-dev/molass-library
Author: Molass Community
Maintainer: Molass Community
License: GNU General Public License v3.0
License-File: LICENSE.txt
Keywords: SEC-SAXS
Classifier: Development Status :: 2 - Pre-Alpha
Classifier: License :: OSI Approved :: GNU General Public License v3 (GPLv3)
Classifier: Programming Language :: Python
Requires-Python: <3.14,>=3.12
Requires-Dist: learnsaxs
Requires-Dist: matplotlib
Requires-Dist: molass-legacy>=0.5.0
Requires-Dist: mrcfile
Requires-Dist: numba
Requires-Dist: numpy
Requires-Dist: psutil
Requires-Dist: pybaselines>=1.2.0
Requires-Dist: ruptures
Requires-Dist: scikit-learn
Requires-Dist: scipy
Requires-Dist: seaborn
Requires-Dist: statsmodels
Requires-Dist: toml
Requires-Dist: tqdm
Provides-Extra: excel
Requires-Dist: pywin32; extra == 'excel'
Provides-Extra: testing
Requires-Dist: pytest; extra == 'testing'
Requires-Dist: pytest-cov; extra == 'testing'
Requires-Dist: pytest-env; extra == 'testing'
Requires-Dist: pytest-order; extra == 'testing'
